persistd/__init__.py
persistd/persist.py
persistd/desktops/__init__.py
persistd/desktops/base_desktop.py
persistd/desktops/virtual_desktop.py
persistd/programs/__init__.py
persistd/programs/base_program.py
persistd/programs/chrome/__init__.py
persistd/programs/chrome/chrome.py
persistd/programs/chrome/extension/background.js
persistd/programs/chrome/extension/manifest.json
persistd/programs/conemu/__init__.py
persistd/programs/conemu/conemu_windows.py
persistd/programs/conemu/startfile_windows.txt
persistd/programs/sublime_text/__init__.py
persistd/programs/sublime_text/default.sublime-project
persistd/programs/sublime_text/sublime_text_windows.py
persistd/settings/__init__.py
persistd/settings/default.py
persistd/settings/local.py
persistd/util/__init__.py
persistd/util/command_line.py
persistd/util/const.py
persistd/util/paths.py
persistd/util/persistable.py
persistd/util/persister.py
persistd/util/savers.py
persistd/util/windows/kill_mutant.bat
persistd/util/windows/handle/Eula.txt
persistd/util/windows/handle/handle.exe
persistd/util/windows/handle/handle64.exe
persistd-1.2.1.dist-info/METADATA
persistd-1.2.1.dist-info/RECORD
persistd-1.2.1.dist-info/WHEEL
persistd-1.2.1.dist-info/entry_points.txt
persistd-1.2.1.dist-info/top_level.txt
