Metadata-Version: 2.1
Name: persistd
Version: 1.2.1
Summary: UNKNOWN
Home-page: https://github.com/dorukkilitcioglu/persistd
Author: Doruk Kilitcioglu
Author-email: doruk.kilitcioglu@gmail.com
License: GPLv3
Platform: UNKNOWN
Classifier: Intended Audience :: Developers
Classifier: License :: OSI Approved :: GNU General Public License v3 (GPLv3)
Classifier: Programming Language :: Python :: 3
Requires-Dist: requests
